finchan_exts/__init__.py
finchan_exts/__version__.py
finchan_exts-0.0.1.dist-info/LICENSE.txt
finchan_exts-0.0.1.dist-info/METADATA
finchan_exts-0.0.1.dist-info/RECORD
finchan_exts-0.0.1.dist-info/WHEEL
finchan_exts-0.0.1.dist-info/top_level.txt
finchan_exts-0.0.1.dist-info/zip-safe
