Metadata-Version: 2.1
Name: finchan-exts
Version: 0.0.1
Summary: a collection of finchan extensions.
Home-page: https://github.com/qytz/finchan_exts
Author: qytz
Author-email: hhhhhf@foxmail.com
License: Apache 2.0
Keywords: finchan
Platform: UNKNOWN
Classifier: Framework :: Robot Framework
Classifier: Development Status :: 3 - Alpha
Classifier: Intended Audience :: Developers
Classifier: Operating System :: POSIX :: Linux
Classifier: License :: OSI Approved :: Apache Software License
Classifier: Natural Language :: Chinese (Simplified)
Classifier: Programming Language :: Python :: 3 :: Only
Classifier: Programming Language :: Python :: 3.6
Requires-Python: >=3.6*
Requires-Dist: click
Requires-Dist: uvloop
Requires-Dist: python-dateutil
Requires-Dist: ruamel.yaml
